cxwidgets/__init__.py
cxwidgets/auxwidgets.py
cxwidgets/bpmwidget.py
cxwidgets/common_mixin.py
cxwidgets/cx_bpm_plot_old.py
cxwidgets/cx_bpmwidget.py
cxwidgets/cx_checkbox.py
cxwidgets/cx_combobox.py
cxwidgets/cx_doublespinbox.py
cxwidgets/cx_label.py
cxwidgets/cx_lcdnumber.py
cxwidgets/cx_led.py
cxwidgets/cx_lineedit.py
cxwidgets/cx_plot.py
cxwidgets/cx_progressbar.py
cxwidgets/cx_pushbutton.py
cxwidgets/cx_spinbox.py
cxwidgets/cx_switch.py
cxwidgets/cxw_demo.py
cxwidgets/pcheckbox.py
cxwidgets/pcombobox.py
cxwidgets/pdoublespinbox.py
cxwidgets/plcdnumber.py
cxwidgets/pledwidget.py
cxwidgets/plt_text.py
cxwidgets/pspinbox.py
cxwidgets/pswitch.py
cxwidgets/pw_demo.py
cxwidgets/aQt/QtCore.py
cxwidgets/aQt/QtDesigner.py
cxwidgets/aQt/QtGui.py
cxwidgets/aQt/QtWidgets.py
cxwidgets/aQt/__init__.py
cxwidgets/aQt/uic.py
cxwidgets/cx_pyqtgraph_items/__init__.py
cxwidgets/cx_pyqtgraph_items/cx_scrollplotdataitem.py
cxwidgets/menus/__init__.py
cxwidgets/menus/doublespinbox_cm.py
cxwidgets/menus/general_cm.py
cxwidgets/menus/spinbox_cm.py
cxwidgets/plugins/__init__.py
cxwidgets/plugins/cx_plugin.py
cxwidgets/plugins/gpaph_plugin.py
cxwidgets/plugins/p_plugin.py
cxwidgets-0.15.dist-info/METADATA
cxwidgets-0.15.dist-info/WHEEL
cxwidgets-0.15.dist-info/top_level.txt
cxwidgets-0.15.dist-info/RECORD
