Metadata-Version: 2.1
Name: cxwidgets
Version: 0.15
Summary: 'PyQt widgets connected to CX v4 control system framewok with designer plugins',
Author: 'Fedor Emanov',
License: GPL
Classifier: License :: OSI Approved :: GNU General Public License (GPL)
Classifier: Programming Language :: Python :: 3
Requires-Python: >=3.3
